atoti_jupyterlab3/LICENSE
atoti_jupyterlab3/__init__.py
atoti_jupyterlab3/_comm_targets.py
atoti_jupyterlab3/_mime_types.py
atoti_jupyterlab3/_plugin.py
atoti_jupyterlab3/_visualize.py
atoti_jupyterlab3/_widget_manager.py
atoti_jupyterlab3/py.typed
atoti_jupyterlab3-0.8.3.data/data/share/jupyter/labextensions/atoti-jupyterlab3/package.json
atoti_jupyterlab3-0.8.3.data/data/share/jupyter/labextensions/atoti-jupyterlab3/static/00b26ac825e2095056396e0553b8ac26d3f8ad158c3826e28b4c45b385c4714a.woff2
atoti_jupyterlab3-0.8.3.data/data/share/jupyter/labextensions/atoti-jupyterlab3/static/07d8e303ce4fc12b4bb54f1004170dd190a1f3db45d400fe68060df3e0897268.ttf
atoti_jupyterlab3-0.8.3.data/data/share/jupyter/labextensions/atoti-jupyterlab3/static/08ce98e51b04d58945a301e639e02b6998af29fdfd61a7b8afdd07bbfc479d4a.ttf
atoti_jupyterlab3-0.8.3.data/data/share/jupyter/labextensions/atoti-jupyterlab3/static/0cdd387c9590a1a9f9794560022dbb59654a7d86f187aa0c81495ad42d3a7308.woff2
atoti_jupyterlab3-0.8.3.data/data/share/jupyter/labextensions/atoti-jupyterlab3/static/0d85ae7cc30f23790a7f1a58c4a112fdca8aae769b6ba11429af1d98b1b6cb3a.ttf
atoti_jupyterlab3-0.8.3.data/data/share/jupyter/labextensions/atoti-jupyterlab3/static/0f60d1b897938ec918c8ce073092411baf9438f6739465693ff18b0f9d20b021.woff2
atoti_jupyterlab3-0.8.3.data/data/share/jupyter/labextensions/atoti-jupyterlab3/static/1020.6d932b0964299c313bae.js
atoti_jupyterlab3-0.8.3.data/data/share/jupyter/labextensions/atoti-jupyterlab3/static/1038.57fe942be0a8467c9b0b.js
atoti_jupyterlab3-0.8.3.data/data/share/jupyter/labextensions/atoti-jupyterlab3/static/1083.28d904971e261150a01a.js
atoti_jupyterlab3-0.8.3.data/data/share/jupyter/labextensions/atoti-jupyterlab3/static/1084.a2faddfc5cf39608b8b2.js
atoti_jupyterlab3-0.8.3.data/data/share/jupyter/labextensions/atoti-jupyterlab3/static/11e4dc8a6471ff6d6ee561d53d10fde8f7489e798257ff449c5d37c197435605.woff
atoti_jupyterlab3-0.8.3.dist-info/LICENSE
atoti_jupyterlab3-0.8.3.dist-info/METADATA
atoti_jupyterlab3-0.8.3.dist-info/WHEEL
atoti_jupyterlab3-0.8.3.dist-info/entry_points.txt
atoti_jupyterlab3-0.8.3.dist-info/top_level.txt
atoti_jupyterlab3-0.8.3.dist-info/RECORD
